converser/__init__.py
converser/conversation_memory/__init__.py
converser/conversation_memory/memory.py
converser/converse/__init__.py
converser/converse/converse.py
converser/models/__init__.py
converser/models/models.py
converser/streaming/__init__.py
converser/streaming/streaming.py
converser/utils/__init__.py
converser/utils/bedrock_runtime_client/__init__.py
converser/utils/bedrock_runtime_client/bedrock_runtime_client.py
converser-0.1.0.dist-info/METADATA
converser-0.1.0.dist-info/WHEEL
converser-0.1.0.dist-info/RECORD
