Metadata-Version: 2.1
Name: converser
Version: 0.1.0
Summary: 
Author: Laith Al-Saadoon
Author-email: alsaadoonlaith@gmail.com
Requires-Python: >=3.8,<4.0
Classifier: Programming Language :: Python :: 3
Classifier: Programming Language :: Python :: 3.8
Classifier: Programming Language :: Python :: 3.9
Classifier: Programming Language :: Python :: 3.10
Classifier: Programming Language :: Python :: 3.11
Classifier: Programming Language :: Python :: 3.12
Requires-Dist: boto3
Requires-Dist: botocore
Requires-Dist: pydantic
Requires-Dist: requests
Requires-Dist: tqdm
